grit/__init__.py
grit/core.py
py_grit-0.0.1a2.dist-info/LICENSE
py_grit-0.0.1a2.dist-info/WHEEL
py_grit-0.0.1a2.dist-info/METADATA
py_grit-0.0.1a2.dist-info/RECORD
