Metadata-Version: 2.1
Name: py-grit
Version: 0.0.1a2
Summary: Exception handling context manager.
Home-page: https://github.com/kilo59/grit
License: MIT
Keywords: context-managers,errors
Author: Gabriel Gore
Author-email: gabriel59kg@gmail.com
Requires-Python: >=3.7.2,<4.0.0
Classifier: Development Status :: 2 - Pre-Alpha
Classifier: License :: OSI Approved :: MIT License
Classifier: Programming Language :: Python :: 3
Classifier: Programming Language :: Python :: 3.10
Classifier: Programming Language :: Python :: 3.7
Classifier: Programming Language :: Python :: 3.8
Classifier: Programming Language :: Python :: 3.9
Classifier: Topic :: Software Development :: Libraries :: Python Modules
Project-URL: Repository, https://github.com/kilo59/grit
